LightwaveExplorer/LightwaveExplorer.py
LightwaveExplorer/__init__.py
lightwaveexplorer-2025.2.4.dist-info/LICENSE
lightwaveexplorer-2025.2.4.dist-info/METADATA
lightwaveexplorer-2025.2.4.dist-info/WHEEL
lightwaveexplorer-2025.2.4.dist-info/top_level.txt
lightwaveexplorer-2025.2.4.dist-info/RECORD
