Metadata-Version: 2.2
Name: LightwaveExplorer
Version: 2025.2.4
Summary: Tools for using Lightwave Explorer results
Author-email: Nick Karpowicz <nicholas.karpowicz@mpq.mpg.de>
License: MIT License
Project-URL: Homepage, https://github.com/NickKarpowicz/LightwaveExplorer
Project-URL: Issues, https://github.com/NickKarpowicz/LightwaveExplorer/issues
Classifier: Programming Language :: Python :: 3
Classifier: Operating System :: OS Independent
Requires-Python: >=3.8
License-File: LICENSE
Requires-Dist: numpy
Requires-Dist: scipy
Requires-Dist: matplotlib
Requires-Dist: pyyaml
